black_sat.cpython-39-x86_64-linux-gnu.so
black_sat-0.10.6.dist-info/METADATA
black_sat-0.10.6.dist-info/WHEEL
black_sat-0.10.6.dist-info/top_level.txt
black_sat-0.10.6.dist-info/RECORD
