Metadata-Version: 2.1
Name: black-sat
Version: 0.10.6
Summary: BLACK Python API
Home-page: https://www.black-sat.org
Author: Nicola Gigante
Author-email: nicola.gigante@unibz.it
License: MIT
Platform: UNKNOWN
Classifier: License :: OSI Approved :: MIT License
Classifier: Topic :: Scientific/Engineering :: Artificial Intelligence
